rlschool/__init__.py
rlschool/liftsim/__init__.py
rlschool/liftsim/config.ini
rlschool/liftsim/environment/__init__.py
rlschool/liftsim/environment/env.py
rlschool/liftsim/environment/animation/__init__.py
rlschool/liftsim/environment/animation/rendering.py
rlschool/liftsim/environment/animation/resources/1.png
rlschool/liftsim/environment/animation/resources/2.png
rlschool/liftsim/environment/animation/resources/3.png
rlschool/liftsim/environment/animation/resources/4.png
rlschool/liftsim/environment/animation/resources/__init__.py
rlschool/liftsim/environment/animation/resources/background.png
rlschool/liftsim/environment/animation/resources/down.png
rlschool/liftsim/environment/animation/resources/line.png
rlschool/liftsim/environment/animation/resources/steady.png
rlschool/liftsim/environment/animation/resources/up.png
rlschool/liftsim/environment/mansion/__init__.py
rlschool/liftsim/environment/mansion/elevator.py
rlschool/liftsim/environment/mansion/mansion_config.py
rlschool/liftsim/environment/mansion/mansion_manager.py
rlschool/liftsim/environment/mansion/test_elevator.py
rlschool/liftsim/environment/mansion/utils.py
rlschool/liftsim/environment/mansion/person_generators/__init__.py
rlschool/liftsim/environment/mansion/person_generators/custom_generator.py
rlschool/liftsim/environment/mansion/person_generators/generator_proxy.py
rlschool/liftsim/environment/mansion/person_generators/mansion_flow.npy
rlschool/liftsim/environment/mansion/person_generators/person_generator.py
rlschool/liftsim/environment/mansion/person_generators/uniform_generator.py
rlschool/metamaze/__init__.py
rlschool/metamaze/keyboard_play_demo_2d.py
rlschool/metamaze/keyboard_play_demo_3d.py
rlschool/metamaze/test.py
rlschool/metamaze/envs/__init__.py
rlschool/metamaze/envs/dynamics.py
rlschool/metamaze/envs/maze_2d.py
rlschool/metamaze/envs/maze_3d.py
rlschool/metamaze/envs/maze_env.py
rlschool/metamaze/envs/maze_gen.py
rlschool/metamaze/envs/ray_caster_utils.py
rlschool-1.0.3.dist-info/LICENSE
rlschool-1.0.3.dist-info/METADATA
rlschool-1.0.3.dist-info/WHEEL
rlschool-1.0.3.dist-info/top_level.txt
rlschool-1.0.3.dist-info/RECORD
