Metadata-Version: 2.1
Name: rlschool
Version: 1.0.3
Summary: RLSchool: Excellent environments for reinforcement Learning benchmarking
Home-page: https://github.com/PaddlePaddle/RLSchool
Author: parl_dev
Author-email: 
License: GPLv3
Platform: UNKNOWN
License-File: LICENSE
Requires-Dist: gym (>=0.18.0)
Requires-Dist: numpy (>=1.16.4)
Requires-Dist: Pillow (>=6.2.2)
Requires-Dist: six (>=1.12.0)
Provides-Extra: liftsim
Requires-Dist: configparser (>=3.7.4) ; extra == 'liftsim'
Requires-Dist: pyglet (==1.4.0) ; (python_version < "3") and extra == 'liftsim'
Requires-Dist: pyglet (==1.5.0) ; (python_version >= "3") and extra == 'liftsim'
Provides-Extra: metamaze
Requires-Dist: pygame (>=2.0.2dev2) ; extra == 'metamaze'
Requires-Dist: numba (>=0.54.0) ; extra == 'metamaze'
Provides-Extra: navigator2d
Requires-Dist: pygame (>=2.0.2dev2) ; extra == 'navigator2d'
Provides-Extra: quadrotor
Requires-Dist: scipy (>=0.12.0) ; extra == 'quadrotor'
Requires-Dist: networkx (>=2.2) ; extra == 'quadrotor'
Requires-Dist: trimesh (>=3.2.39) ; extra == 'quadrotor'
Requires-Dist: colour (>=0.1.5) ; extra == 'quadrotor'
Provides-Extra: quadrupedal
Requires-Dist: scipy (>=0.12.0) ; extra == 'quadrupedal'
Requires-Dist: pybullet (>=3.0.7) ; extra == 'quadrupedal'
Requires-Dist: attrs (>=20.3.0) ; extra == 'quadrupedal'
